dirmeta/__init__.py
dirmeta/scanner.py
dirmeta/viewer.py
dirmeta-0.1.dist-info/licenses/LICENSE
dirmeta-0.1.dist-info/METADATA
dirmeta-0.1.dist-info/WHEEL
dirmeta-0.1.dist-info/entry_points.txt
dirmeta-0.1.dist-info/top_level.txt
dirmeta-0.1.dist-info/RECORD
