Metadata-Version: 2.4
Name: dirmeta
Version: 0.1
Summary: A CLI tool to scan filesystem directory structures and view the captured metadata.
Author-email: Saptarshi Chakrabarti | LISCO <saptarshi.chakrabarti@kuleuven.be>
License: MIT License
Project-URL: Homepage, https://github.com/saptarshichakrabarti/dirmeta
Project-URL: Repository, https://github.com/saptarshichakrabarti/dirmeta
Keywords: filesystem,metadata,directory,scan,structure,tree,cli,utility,file management
Classifier: Environment :: Console
Classifier: Intended Audience :: Developers
Classifier: Intended Audience :: End Users/Desktop
Classifier: License :: OSI Approved :: MIT License
Classifier: Operating System :: OS Independent
Classifier: Programming Language :: Python :: 3
Classifier: Programming Language :: Python :: 3 :: Only
Classifier: Programming Language :: Python :: 3.7
Classifier: Programming Language :: Python :: 3.8
Classifier: Programming Language :: Python :: 3.9
Classifier: Programming Language :: Python :: 3.10
Classifier: Programming Language :: Python :: 3.11
Classifier: Programming Language :: Python :: 3.12
Classifier: Topic :: System :: Filesystems
Classifier: Topic :: Utilities
Requires-Python: >=3.7
License-File: LICENSE
Dynamic: license-file
